.flake8
noxfile.py
options_reticle/__init__.py
options_reticle/builder.py
options_reticle/core.py
options_reticle/downloader.py
options_reticle/emoji.py
options_reticle/options.py
options_reticle/paths.py
options_reticle/templates/emoji.pine
options_reticle/templates/fill.pine
options_reticle/templates/head.pine
options_reticle/templates/label.pine
options_reticle/templates/option_function.pine
options_reticle/templates/reticle.pine
options_reticle/templates/variables.pine
options_reticle/tradingview.py
poetry.lock
options_reticle-0.3.1.dist-info/entry_points.txt
options_reticle-0.3.1.dist-info/LICENSE
options_reticle-0.3.1.dist-info/WHEEL
options_reticle-0.3.1.dist-info/METADATA
options_reticle-0.3.1.dist-info/RECORD
