Metadata-Version: 2.1
Name: options-reticle
Version: 0.3.1
Summary: Generate OTM strike targets from tradingview watchlists.
Home-page: https://github.com/dgnsrekt/tradingview-options-reticle
License: MIT
Keywords: tradingview,options-trading,python
Author: dgnsrekt
Author-email: dgnsrekt@pm.me
Requires-Python: >=3.8,<4.0
Classifier: License :: OSI Approved :: MIT License
Classifier: Programming Language :: Python :: 3
Classifier: Programming Language :: Python :: 3.8
Classifier: Programming Language :: Python :: 3.9
Requires-Dist: jinja2 (>=2.11.2,<3.0.0)
Requires-Dist: more-itertools (>=8.5.0,<9.0.0)
Requires-Dist: pendulum (>=2.1.2,<3.0.0)
Requires-Dist: pydantic (>=1.6.1,<2.0.0)
Requires-Dist: requests-whaor (>=0.2.1,<0.3.0)
Requires-Dist: toml (>=0.10.1,<0.11.0)
Requires-Dist: typer[all] (>=0.3.2,<0.4.0)
Requires-Dist: yfs (>=0.3.1,<0.4.0)
Project-URL: Documentation, https://github.com/dgnsrekt/tradingview-options-reticle
Project-URL: Repository, https://github.com/dgnsrekt/tradingview-options-reticle
